anomaly_toolbox/__init__.py
anomaly_toolbox/hps.py
anomaly_toolbox/datasets/__init__.py
anomaly_toolbox/datasets/corrupted_mnist.py
anomaly_toolbox/datasets/dataset.py
anomaly_toolbox/datasets/mnist.py
anomaly_toolbox/datasets/mvtecad.py
anomaly_toolbox/datasets/surface_cracks.py
anomaly_toolbox/experiments/__init__.py
anomaly_toolbox/experiments/anogan.py
anomaly_toolbox/experiments/descargan.py
anomaly_toolbox/experiments/egbad.py
anomaly_toolbox/experiments/experiment.py
anomaly_toolbox/experiments/ganomaly.py
anomaly_toolbox/losses/__init__.py
anomaly_toolbox/losses/egbad.py
anomaly_toolbox/losses/ganomaly.py
anomaly_toolbox/models/__init__.py
anomaly_toolbox/models/anogan.py
anomaly_toolbox/models/descargan.py
anomaly_toolbox/models/egbad.py
anomaly_toolbox/models/ganomaly.py
anomaly_toolbox/predictors/__init__.py
anomaly_toolbox/predictors/ganomaly.py
anomaly_toolbox/trainers/__init__.py
anomaly_toolbox/trainers/anogan.py
anomaly_toolbox/trainers/descargan.py
anomaly_toolbox/trainers/egbad.py
anomaly_toolbox/trainers/ganomaly.py
anomaly_toolbox/trainers/trainer.py
anomaly_toolbox-0.1.2.data/scripts/anomaly-box.py
anomaly_toolbox-0.1.2.dist-info/LICENSE
anomaly_toolbox-0.1.2.dist-info/METADATA
anomaly_toolbox-0.1.2.dist-info/WHEEL
anomaly_toolbox-0.1.2.dist-info/top_level.txt
anomaly_toolbox-0.1.2.dist-info/RECORD
