Metadata-Version: 2.1
Name: anomaly-toolbox
Version: 0.1.2
Summary: Anomaly Toolbox Powered by GANs
Home-page: https://github.com/zurutech/anomaly-toolbox
Author: Zuru Tech HK Limited, All rights reserved.
Author-email: ml@zuru.tech
License: MIT license
Keywords: anomaly_toolbox
Platform: UNKNOWN
Classifier: Development Status :: 2 - Pre-Alpha
Classifier: Intended Audience :: Developers
Classifier: License :: OSI Approved :: MIT License
Classifier: Natural Language :: English
Classifier: Programming Language :: Python :: 3.7
Requires-Python: >=3.8
Requires-Dist: tensorboard
Requires-Dist: numpy
Requires-Dist: click
Requires-Dist: tensorflow
Requires-Dist: tensorflow-datasets
Requires-Dist: requests
Requires-Dist: rarfile
Requires-Dist: tabulate
